modelprop/__init__.py
modelprop/detect.py
modelprop-0.1.0.dist-info/LICENSE
modelprop-0.1.0.dist-info/METADATA
modelprop-0.1.0.dist-info/WHEEL
modelprop-0.1.0.dist-info/top_level.txt
modelprop-0.1.0.dist-info/RECORD
